subseasonal_toolkit/__init__.py
subseasonal_toolkit/batch_crps.py
subseasonal_toolkit/batch_metrics.py
subseasonal_toolkit/generate_predictions.py
subseasonal_toolkit/models/abc/abc.ipynb
subseasonal_toolkit/models/abc/abc_util.py
subseasonal_toolkit/models/abc/attributes.py
subseasonal_toolkit/models/abc/batch_predict.py
subseasonal_toolkit/models/abc/selected_submodel.json
subseasonal_toolkit/models/abc_ccsm4/attributes.py
subseasonal_toolkit/models/abc_ccsm4/selected_submodel.json
subseasonal_toolkit/models/abc_cfsv2/attributes.py
subseasonal_toolkit/models/abc_cfsv2/selected_submodel.json
subseasonal_toolkit/models/abc_ecmwf/attributes.py
subseasonal_toolkit/models/abc_ecmwf/bulk_batch_predict.py
subseasonal_toolkit/models/abc_ecmwf/selected_submodel.json
subseasonal_toolkit/models/abc_fimr1p1/attributes.py
subseasonal_toolkit/models/abc_fimr1p1/selected_submodel.json
subseasonal_toolkit/models/abc_gefs/attributes.py
subseasonal_toolkit/models/abc_gefs/selected_submodel.json
subseasonal_toolkit/models/abc_gem/attributes.py
subseasonal_toolkit/models/abc_gem/selected_submodel.json
subseasonal_toolkit/models/abc_geos_v2p1/attributes.py
subseasonal_toolkit/models/abc_geos_v2p1/selected_submodel.json
subseasonal_toolkit/models/abc_nesm/attributes.py
subseasonal_toolkit/models/abc_nesm/selected_submodel.json
subseasonal_toolkit/models/abc_subx_mean/attributes.py
subseasonal_toolkit/models/abc_subx_mean/selected_submodel.json
subseasonal_toolkit/models/abcds_ecmwf/attributes.py
subseasonal_toolkit/models/abcds_ecmwf/selected_submodel.json
subseasonal_toolkit/models/autoknn/attributes.py
subseasonal_toolkit/models/autoknn/autoknn.ipynb
subseasonal_toolkit/models/autoknn/autoknn_util.py
subseasonal_toolkit/models/autoknn/batch_predict.py
subseasonal_toolkit/models/autoknn/cluster_params.json
subseasonal_toolkit/models/autoknn/selected_submodel.json
subseasonal_toolkit/models/ccsm4pp/attributes.py
subseasonal_toolkit/models/ccsm4pp/batch_predict.py
subseasonal_toolkit-0.1.1.dist-info/LICENSE
subseasonal_toolkit-0.1.1.dist-info/METADATA
subseasonal_toolkit-0.1.1.dist-info/WHEEL
subseasonal_toolkit-0.1.1.dist-info/top_level.txt
subseasonal_toolkit-0.1.1.dist-info/RECORD
