Metadata-Version: 2.1
Name: subseasonal_toolkit
Version: 0.1.1
Summary: Models for subseasonal forecasting of temperature and precipitation 2-6 weeks in advance.
Home-page: https://github.com/microsoft/subseasonal_toolkit
License-File: LICENSE
Requires-Dist: numpy
Requires-Dist: pandas
Requires-Dist: scikit-learn
Requires-Dist: jupyter
Requires-Dist: filelock
Requires-Dist: catboost
Requires-Dist: pyarrow
Requires-Dist: ttictoc
Requires-Dist: subseasonal-data
Requires-Dist: poold
Requires-Dist: torch
Requires-Dist: nbeats-pytorch
Requires-Dist: pytorch-lightning
Requires-Dist: tables
